Pokeapi/__init__.py
Pokeapi/pokemon.csv
Pokeapi/random_pokemon.py
PokeapiMHM-1.0.0.dist-info/METADATA
PokeapiMHM-1.0.0.dist-info/WHEEL
PokeapiMHM-1.0.0.dist-info/top_level.txt
PokeapiMHM-1.0.0.dist-info/RECORD
